{"cameraMode":{"drawMode":0,"name":"Shaded","section":"Shading Mode"},"sceneLighting":true,"audioPlay":false,"sceneViewState":{"m_AlwaysRefresh":false,"showFog":true,"showSkybox":true,"showFlares":true,"showImageEffects":true,"showParticleSystems":true,"showVisualEffectGraphs":true,"m_FxEnabled":true},"in2DMode":false,"pivot":{"x":602.2401733398438,"y":185.05894470214845,"z":569.9189453125},"rotation":{"x":0.0827145054936409,"y":-0.00299474922940135,"z":0.0002454475616104901,"w":0.9965742230415344},"size":470.53570556640627,"orthographic":false}