{"cameraMode":{"drawMode":0,"name":"Shaded","section":"Shading Mode"},"sceneLighting":true,"audioPlay":false,"sceneViewState":{"m_AlwaysRefresh":false,"showFog":true,"showSkybox":true,"showFlares":true,"showImageEffects":true,"showParticleSystems":true,"showVisualEffectGraphs":true,"m_FxEnabled":true},"in2DMode":false,"pivot":{"x":477.60186767578127,"y":12.381662368774414,"z":445.1459655761719},"rotation":{"x":-0.08440060913562775,"y":-0.33905282616615298,"z":0.030832577496767045,"w":-0.9361563324928284},"size":10.0,"orthographic":false}